flask_ory_auth/__init__.py
flask_ory_auth/hydra/client.py
flask_ory_auth/hydra/middleware.py
flask_ory_auth/keto/client.py
flask_ory_auth/keto/middleware.py
flask_ory_auth/kratos/client.py
flask_ory_auth/kratos/middleware.py
flask_ory_auth-0.1.7.dist-info/LICENSE
flask_ory_auth-0.1.7.dist-info/WHEEL
flask_ory_auth-0.1.7.dist-info/METADATA
flask_ory_auth-0.1.7.dist-info/RECORD
