Metadata-Version: 2.1
Name: flask-ory-auth
Version: 0.1.7
Summary: Useful middlewares and clients to use Ory products in flask App
Author: Andrew Minkin
Author-email: minkin.andrew@gmail.com
Requires-Python: >=3.7
Classifier: Programming Language :: Python :: 3
Classifier: Programming Language :: Python :: 3.10
Classifier: Programming Language :: Python :: 3.7
Classifier: Programming Language :: Python :: 3.8
Classifier: Programming Language :: Python :: 3.9
Requires-Dist: Flask (>=2.1.2,<3.0.0)
Requires-Dist: requests (>=2.28.0,<3.0.0)
Requires-Dist: requests-oauthlib (>=1.3.1,<2.0.0)
